esntorch/__init__.py
esntorch/core/__init__.py
esntorch/core/esn.py
esntorch/core/learning_algo.py
esntorch/core/pooling_strategy.py
esntorch/core/reservoir.py
esntorch/utils/__init__.py
esntorch/utils/embedding.py
esntorch/utils/matrix.py
tests/__init__.py
tests/core/__init__.py
tests/core/test_esn.py
tests/core/test_learning_algo.py
tests/core/test_pooling_strategy.py
tests/core/test_reservoir.py
tests/utils/__init__.py
tests/utils/test_embedding.py
tests/utils/test_matrix.py
esntorch-1.0.6.dist-info/LICENSE
esntorch-1.0.6.dist-info/METADATA
esntorch-1.0.6.dist-info/WHEEL
esntorch-1.0.6.dist-info/top_level.txt
esntorch-1.0.6.dist-info/RECORD
