Metadata-Version: 2.1
Name: esntorch
Version: 1.0.6
Summary: Python library: Echo state Networks for NLP
Home-page: 
Author: Playtika Ltd.
Author-email: 
License: MIT License
Classifier: Programming Language :: Python :: 3
Classifier: Operating System :: OS Independent
Requires-Python: >=3.7
License-File: LICENSE
Requires-Dist: datasets (==1.7.0)
Requires-Dist: ipywidgets (==7.7.1)
Requires-Dist: numpy (==1.22.3)
Requires-Dist: pytest (==6.2.4)
Requires-Dist: scikit-learn (==1.1.2)
Requires-Dist: setuptools (==63.4.2)
Requires-Dist: torch (==1.7.1)
Requires-Dist: tqdm (==4.49.0)
Requires-Dist: transformers (==4.8.2)
